Metadata-Version: 2.1
Name: photosdup
Version: 2.3
Summary: Photos Duplicate finder - searches for duplicate or similar images in a Mac Photos library.
Home-page: https://github.com/peter-sk/photosdup
Author: Peter Schneider-Kamp
Author-email: petersk@imada.sdu.dk
License: MIT
Keywords: mac,photos,duplicate,finder
Classifier: Development Status :: 5 - Production/Stable
Classifier: Intended Audience :: Developers
Classifier: Topic :: Software Development :: Build Tools
Classifier: License :: OSI Approved :: MIT License
Classifier: Programming Language :: Python :: 3.9
License-File: LICENSE
